chatollamaagent/__init__.py
chatollamaagent/config.json
chatollamaagent/config.py
chatollamaagent/documentation.md
chatollamaagent/interface.py
chatollamaagent/runner.py
chatollamaagent/nodes/__init__.py
chatollamaagent/nodes/base.py
chatollamaagent/nodes/builtin.py
chatollamaagent/nodes/custom_socket_interface.md
chatollamaagent/nodes/working_with_custom_sockets.md
chatollamaagent/web/static/css/style.css
chatollamaagent/web/static/js/main.js
chatollamaagent/web/static/js/node-editor.js
chatollamaagent/web/static/js/node-interface.js
chatollamaagent/web/static/js/node-palette.js
chatollamaagent/web/static/js/node-registry.js
chatollamaagent/web/static/js/settings.js
chatollamaagent/web/static/js/sidebar-resize.js
chatollamaagent/web/static/js/statistics.js
chatollamaagent/web/static/js/websocket.js
chatollamaagent/web/templates/index.html
chatollamaagent-0.15.dist-info/LICENSE
chatollamaagent-0.15.dist-info/METADATA
chatollamaagent-0.15.dist-info/WHEEL
chatollamaagent-0.15.dist-info/top_level.txt
chatollamaagent-0.15.dist-info/RECORD
