Metadata-Version: 2.1
Name: chatollamaagent
Version: 0.15
Summary: A visual node-based programming system for creating and managing agent-based workflows.
Author: Matthew Sanchez
Author-email: 
Classifier: Programming Language :: Python :: 3
Classifier: License :: OSI Approved :: MIT License
Classifier: Operating System :: OS Independent
Requires-Python: >=3.10
License-File: LICENSE
Requires-Dist: chatollama
Requires-Dist: websockets
